aiqwal/__init__.py
aiqwal/config.py
aiqwal/database_manager.py
aiqwal/db_connector.py
aiqwal/executor.py
aiqwal/nlp_response_generator.py
aiqwal/query_generator.py
aiqwal/schema_cache.py
aiqwal/session.py
aiqwal/ultimate_database_manager.py
aiqwal/ultimate_executor.py
aiqwal/ultimate_query_generator.py
aiqwal/utils.py
aiqwal-1.0.0.dist-info/licenses/LICENSE
aiqwal-1.0.0.dist-info/METADATA
aiqwal-1.0.0.dist-info/WHEEL
aiqwal-1.0.0.dist-info/entry_points.txt
aiqwal-1.0.0.dist-info/top_level.txt
aiqwal-1.0.0.dist-info/RECORD
