Metadata-Version: 2.4
Name: aiqwal
Version: 1.0.0
Summary: AI Query Writer for Any Language - Universal SQL generator that works with ANY database
Home-page: https://github.com/shivnathtathe/aiqwal
Author: Shivnath tathe
Author-email: sptathe2001@gmail.com
Keywords: ai sql database natural-language llm sqlalchemy query-generator
Classifier: Development Status :: 4 - Beta
Classifier: Intended Audience :: Developers
Classifier: Topic :: Database
Classifier: Topic :: Scientific/Engineering :: Artificial Intelligence
Classifier: License :: OSI Approved :: MIT License
Classifier: Programming Language :: Python :: 3
Classifier: Programming Language :: Python :: 3.8
Classifier: Programming Language :: Python :: 3.9
Classifier: Programming Language :: Python :: 3.10
Classifier: Programming Language :: Python :: 3.11
Classifier: Programming Language :: Python :: 3.12
Requires-Python: >=3.8
License-File: LICENSE
Requires-Dist: sqlalchemy
Requires-Dist: llama-cpp-python
Provides-Extra: dev
Requires-Dist: pytest>=6.0; extra == "dev"
Requires-Dist: pytest-cov; extra == "dev"
Requires-Dist: black; extra == "dev"
Requires-Dist: flake8; extra == "dev"
Requires-Dist: mypy; extra == "dev"
Provides-Extra: all
Requires-Dist: psycopg2-binary; extra == "all"
Requires-Dist: pymysql; extra == "all"
Requires-Dist: pyodbc; extra == "all"
Requires-Dist: cx-oracle; extra == "all"
Requires-Dist: snowflake-sqlalchemy; extra == "all"
Requires-Dist: pybigquery; extra == "all"
Requires-Dist: redshift-connector; extra == "all"
Requires-Dist: pymongo; extra == "all"
Dynamic: author
Dynamic: author-email
Dynamic: classifier
Dynamic: description
Dynamic: description-content-type
Dynamic: home-page
Dynamic: keywords
Dynamic: license-file
Dynamic: provides-extra
Dynamic: requires-dist
Dynamic: requires-python
Dynamic: summary
